dmodels/__init__.py
dmodels/admin.py
dmodels/apps.py
dmodels/models.py
dmodels/migrations/__init__.py
dmodels-0.1.dev0.dist-info/LICENSE.txt
dmodels-0.1.dev0.dist-info/METADATA
dmodels-0.1.dev0.dist-info/WHEEL
dmodels-0.1.dev0.dist-info/top_level.txt
dmodels-0.1.dev0.dist-info/RECORD
